{
    "version": "6.1.0",
    "description": "Comic and manga converter for ebook readers.",
    "homepage": "https://github.com/ciromattia/kcc",
    "license": "ISC",
    "depends": "extras/kindlegen",
    "architecture": {
        "64bit": {
            "url": "https://kcc.iosphe.re/Windows/KindleComicConverter_win_6.1.0.exe",
            "hash": "8334ccab77288bee8ef2e7108eca445deaa0ecad643f61db707e64a0a7e6f7fc",
            "shortcuts": [
                [
                    "KCC.exe",
                    "Kindle Comic Converter"
                ]
            ]
        }
    },
    "innosetup": true,
    "checkver": "github",
    "autoupdate": {
        "architecture": {
            "64bit": {
                "url": "https://kcc.iosphe.re/Windows/KindleComicConverter_win_$version.exe"
            }
        }
    }
}
